[
 {
  "path": "/home/jameschong/Projects/audits-kd/workspace/datasets/DAppSCAN/DAppSCAN-source/contracts/Hacken-Seedefi Fund/code/InitializableERC20.sol",
  "ast": {
   "type": "SourceUnit",
   "children": [
    {
     "type": "PragmaDirective",
     "name": "solidity",
     "value": "0.6.9"
    },
    {
     "type": "ContractDefinition",
     "name": "SafeMath",
     "baseContracts": [],
     "subNodes": [
      {
       "type": "FunctionDefinition",
       "name": "mul",
       "parameters": [
        {
         "type": "VariableDeclaration",
         "typeName": {
          "type": "ElementaryTypeName",
          "name": "uint256",
          "stateMutability": null
         },
         "name": "a",
         "identifier": {
          "type": "Identifier",
          "name": "a"
         },
         "storageLocation": null,
         "isStateVar": false,
         "isIndexed": false,
         "expression": null
        },
        {
         "type": "VariableDeclaration",
         "typeName": {
          "type": "ElementaryTypeName",
          "name": "uint256",
          "stateMutability": null
         },
         "name": "b",
         "identifier": {
          "type": "Identifier",
          "name": "b"
         },
         "storageLocation": null,
         "isStateVar": false,
         "isIndexed": false,
         "expression": null
        }
       ],
       "returnParameters": [
        {
         "type": "VariableDeclaration",
         "typeName": {
          "type": "ElementaryTypeName",
          "name": "uint256",
          "stateMutability": null
         },
         "name": null,
         "identifier": null,
         "storageLocation": null,
         "isStateVar": false,
         "isIndexed": false,
         "expression": null
        }
       ],
       "body": {
        "type": "Block",
        "statements": [
         {
          "type": "IfStatement",
          "condition": {
           "type": "BinaryOperation",
           "operator": "==",
           "left": {
            "type": "Identifier",
            "name": "a"
           },
           "right": {
            "type": "NumberLiteral",
            "number": "0",
            "subdenomination": null
           }
          },
          "trueBody": {
           "type": "Block",
           "statements": [
            {
             "type": "ReturnStatement",
             "expression": {
              "type": "NumberLiteral",
              "number": "0",
              "subdenomination": null
             }
            }
           ]
          },
          "falseBody": null
         },
         {
          "type": "VariableDeclarationStatement",
          "variables": [
           {
            "type": "VariableDeclaration",
            "typeName": {
             "type": "ElementaryTypeName",
             "name": "uint256",
             "stateMutability": null
            },
            "name": "c",
            "identifier": {
             "type": "Identifier",
             "name": "c"
            },
            "storageLocation": null,
            "isStateVar": false,
            "isIndexed": false,
            "expression": null
           }
          ],
          "initialValue": {
           "type": "BinaryOperation",
           "operator": "*",
           "left": {
            "type": "Identifier",
            "name": "a"
           },
           "right": {
            "type": "Identifier",
            "name": "b"
           }
          }
         },
         {
          "type": "ExpressionStatement",
          "expression": {
           "type": "FunctionCall",
           "expression": {
            "type": "Identifier",
            "name": "require"
           },
           "arguments": [
            {
             "type": "BinaryOperation",
             "operator": "==",
             "left": {
              "type": "BinaryOperation",
              "operator": "/",
              "left": {
               "type": "Identifier",
               "name": "c"
              },
              "right": {
               "type": "Identifier",
               "name": "a"
              }
             },
             "right": {
              "type": "Identifier",
              "name": "b"
             }
            },
            {
             "type": "StringLiteral",
             "value": "MUL_ERROR",
             "parts": [
              "MUL_ERROR"
             ],
             "isUnicode": [
              false
             ]
            }
           ],
           "names": [],
           "identifiers": []
          }
         },
         {
          "type": "ReturnStatement",
          "expression": {
           "type": "Identifier",
           "name": "c"
          }
         }
        ]
       },
       "visibility": "internal",
       "modifiers": [],
       "override": null,
       "isConstructor": false,
       "isReceiveEther": false,
       "isFallback": false,
       "isVirtual": false,
       "stateMutability": "pure"
      },
      {
       "type": "FunctionDefinition",
       "name": "div",
       "parameters": [
        {
         "type": "VariableDeclaration",
         "typeName": {
          "type": "ElementaryTypeName",
          "name": "uint256",
          "stateMutability": null
         },
         "name": "a",
         "identifier": {
          "type": "Identifier",
          "name": "a"
         },
         "storageLocation": null,
         "isStateVar": false,
         "isIndexed": false,
         "expression": null
        },
        {
         "type": "VariableDeclaration",
         "typeName": {
          "type": "ElementaryTypeName",
          "name": "uint256",
          "stateMutability": null
         },
         "name": "b",
         "identifier": {
          "type": "Identifier",
          "name": "b"
         },
         "storageLocation": null,
         "isStateVar": false,
         "isIndexed": false,
         "expression": null
        }
       ],
       "returnParameters": [
        {
         "type": "VariableDeclaration",
         "typeName": {
          "type": "ElementaryTypeName",
          "name": "uint256",
          "stateMutability": null
         },
         "name": null,
         "identifier": null,
         "storageLocation": null,
         "isStateVar": false,
         "isIndexed": false,
         "expression": null
        }
       ],
       "body": {
        "type": "Block",
        "statements": [
         {
          "type": "ExpressionStatement",
          "expression": {
           "type": "FunctionCall",
           "expression": {
            "type": "Identifier",
            "name": "require"
           },
           "arguments": [
            {
             "type": "BinaryOperation",
             "operator": ">",
             "left": {
              "type": "Identifier",
              "name": "b"
             },
             "right": {
              "type": "NumberLiteral",
              "number": "0",
              "subdenomination": null
             }
            },
            {
             "type": "StringLiteral",
             "value": "DIVIDING_ERROR",
             "parts": [
              "DIVIDING_ERROR"
             ],
             "isUnicode": [
              false
             ]
            }
           ],
           "names": [],
           "identifiers": []
          }
         },
         {
          "type": "ReturnStatement",
          "expression": {
           "type": "BinaryOperation",
           "operator": "/",
           "left": {
            "type": "Identifier",
            "name": "a"
           },
           "right": {
            "type": "Identifier",
            "name": "b"
           }
          }
         }
        ]
       },
       "visibility": "internal",
       "modifiers": [],
       "override": null,
       "isConstructor": false,
       "isReceiveEther": false,
       "isFallback": false,
       "isVirtual": false,
       "stateMutability": "pure"
      },
      {
       "type": "FunctionDefinition",
       "name": "divCeil",
       "parameters": [
        {
         "type": "VariableDeclaration",
         "typeName": {
          "type": "ElementaryTypeName",
          "name": "uint256",
          "stateMutability": null
         },
         "name": "a",
         "identifier": {
          "type": "Identifier",
          "name": "a"
         },
         "storageLocation": null,
         "isStateVar": false,
         "isIndexed": false,
         "expression": null
        },
        {
         "type": "VariableDeclaration",
         "typeName": {
          "type": "ElementaryTypeName",
          "name": "uint256",
          "stateMutability": null
         },
         "name": "b",
         "identifier": {
          "type": "Identifier",
          "name": "b"
         },
         "storageLocation": null,
         "isStateVar": false,
         "isIndexed": false,
         "expression": null
        }
       ],
       "returnParameters": [
        {
         "type": "VariableDeclaration",
         "typeName": {
          "type": "ElementaryTypeName",
          "name": "uint256",
          "stateMutability": null
         },
         "name": null,
         "identifier": null,
         "storageLocation": null,
         "isStateVar": false,
         "isIndexed": false,
         "expression": null
        }
       ],
       "body": {
        "type": "Block",
        "statements": [
         {
          "type": "VariableDeclarationStatement",
          "variables": [
           {
            "type": "VariableDeclaration",
            "typeName": {
             "type": "ElementaryTypeName",
             "name": "uint256",
             "stateMutability": null
            },
            "name": "quotient",
            "identifier": {
             "type": "Identifier",
             "name": "quotient"
            },
            "storageLocation": null,
            "isStateVar": false,
            "isIndexed": false,
            "expression": null
           }
          ],
          "initialValue": {
           "type": "FunctionCall",
           "expression": {
            "type": "Identifier",
            "name": "div"
           },
           "arguments": [
            {
             "type": "Identifier",
             "name": "a"
            },
            {
             "type": "Identifier",
             "name": "b"
            }
           ],
           "names": [],
           "identifiers": []
          }
         },
         {
          "type": "VariableDeclarationStatement",
          "variables": [
           {
            "type": "VariableDeclaration",
            "typeName": {
             "type": "ElementaryTypeName",
             "name": "uint256",
             "stateMutability": null
            },
            "name": "remainder",
            "identifier": {
             "type": "Identifier",
             "name": "remainder"
            },
            "storageLocation": null,
            "isStateVar": false,
            "isIndexed": false,
            "expression": null
           }
          ],
          "initialValue": {
           "type": "BinaryOperation",
           "operator": "-",
           "left": {
            "type": "Identifier",
            "name": "a"
           },
           "right": {
            "type": "BinaryOperation",
            "operator": "*",
            "left": {
             "type": "Identifier",
             "name": "quotient"
            },
            "right": {
             "type": "Identifier",
             "name": "b"
            }
           }
          }
         },
         {
          "type": "IfStatement",
          "condition": {
           "type": "BinaryOperation",
           "operator": ">",
           "left": {
            "type": "Identifier",
            "name": "remainder"
           },
           "right": {
            "type": "NumberLiteral",
            "number": "0",
            "subdenomination": null
           }
          },
          "trueBody": {
           "type": "Block",
           "statements": [
            {
             "type": "ReturnStatement",
             "expression": {
              "type": "BinaryOperation",
              "operator": "+",
              "left": {
               "type": "Identifier",
               "name": "quotient"
              },
              "right": {
               "type": "NumberLiteral",
               "number": "1",
               "subdenomination": null
              }
             }
            }
           ]
          },
          "falseBody": {
           "type": "Block",
           "statements": [
            {
             "type": "ReturnStatement",
             "expression": {
              "type": "Identifier",
              "name": "quotient"
             }
            }
           ]
          }
         }
        ]
       },
       "visibility": "internal",
       "modifiers": [],
       "override": null,
       "isConstructor": false,
       "isReceiveEther": false,
       "isFallback": false,
       "isVirtual": false,
       "stateMutability": "pure"
      },
      {
       "type": "FunctionDefinition",
       "name": "sub",
       "parameters": [
        {
         "type": "VariableDeclaration",
         "typeName": {
          "type": "ElementaryTypeName",
          "name": "uint256",
          "stateMutability": null
         },
         "name": "a",
         "identifier": {
          "type": "Identifier",
          "name": "a"
         },
         "storageLocation": null,
         "isStateVar": false,
         "isIndexed": false,
         "expression": null
        },
        {
         "type": "VariableDeclaration",
         "typeName": {
          "type": "ElementaryTypeName",
          "name": "uint256",
          "stateMutability": null
         },
         "name": "b",
         "identifier": {
          "type": "Identifier",
          "name": "b"
         },
         "storageLocation": null,
         "isStateVar": false,
         "isIndexed": false,
         "expression": null
        }
       ],
       "returnParameters": [
        {
         "type": "VariableDeclaration",
         "typeName": {
          "type": "ElementaryTypeName",
          "name": "uint256",
          "stateMutability": null
         },
         "name": null,
         "identifier": null,
         "storageLocation": null,
         "isStateVar": false,
         "isIndexed": false,
         "expression": null
        }
       ],
       "body": {
        "type": "Block",
        "statements": [
         {
          "type": "ExpressionStatement",
          "expression": {
           "type": "FunctionCall",
           "expression": {
            "type": "Identifier",
            "name": "require"
           },
           "arguments": [
            {
             "type": "BinaryOperation",
             "operator": "<=",
             "left": {
              "type": "Identifier",
              "name": "b"
             },
             "right": {
              "type": "Identifier",
              "name": "a"
             }
            },
            {
             "type": "StringLiteral",
             "value": "SUB_ERROR",
             "parts": [
              "SUB_ERROR"
             ],
             "isUnicode": [
              false
             ]
            }
           ],
           "names": [],
           "identifiers": []
          }
         },
         {
          "type": "ReturnStatement",
          "expression": {
           "type": "BinaryOperation",
           "operator": "-",
           "left": {
            "type": "Identifier",
            "name": "a"
           },
           "right": {
            "type": "Identifier",
            "name": "b"
           }
          }
         }
        ]
       },
       "visibility": "internal",
       "modifiers": [],
       "override": null,
       "isConstructor": false,
       "isReceiveEther": false,
       "isFallback": false,
       "isVirtual": false,
       "stateMutability": "pure"
      },
      {
       "type": "FunctionDefinition",
       "name": "add",
       "parameters": [
        {
         "type": "VariableDeclaration",
         "typeName": {
          "type": "ElementaryTypeName",
          "name": "uint256",
          "stateMutability": null
         },
         "name": "a",
         "identifier": {
          "type": "Identifier",
          "name": "a"
         },
         "storageLocation": null,
         "isStateVar": false,
         "isIndexed": false,
         "expression": null
        },
        {
         "type": "VariableDeclaration",
         "typeName": {
          "type": "ElementaryTypeName",
          "name": "uint256",
          "stateMutability": null
         },
         "name": "b",
         "identifier": {
          "type": "Identifier",
          "name": "b"
         },
         "storageLocation": null,
         "isStateVar": false,
         "isIndexed": false,
         "expression": null
        }
       ],
       "returnParameters": [
        {
         "type": "VariableDeclaration",
         "typeName": {
          "type": "ElementaryTypeName",
          "name": "uint256",
          "stateMutability": null
         },
         "name": null,
         "identifier": null,
         "storageLocation": null,
         "isStateVar": false,
         "isIndexed": false,
         "expression": null
        }
       ],
       "body": {
        "type": "Block",
        "statements": [
         {
          "type": "VariableDeclarationStatement",
          "variables": [
           {
            "type": "VariableDeclaration",
            "typeName": {
             "type": "ElementaryTypeName",
             "name": "uint256",
             "stateMutability": null
            },
            "name": "c",
            "identifier": {
             "type": "Identifier",
             "name": "c"
            },
            "storageLocation": null,
            "isStateVar": false,
            "isIndexed": false,
            "expression": null
           }
          ],
          "initialValue": {
           "type": "BinaryOperation",
           "operator": "+",
           "left": {
            "type": "Identifier",
            "name": "a"
           },
           "right": {
            "type": "Identifier",
            "name": "b"
           }
          }
         },
         {
          "type": "ExpressionStatement",
          "expression": {
           "type": "FunctionCall",
           "expression": {
            "type": "Identifier",
            "name": "require"
           },
           "arguments": [
            {
             "type": "BinaryOperation",
             "operator": ">=",
             "left": {
              "type": "Identifier",
              "name": "c"
             },
             "right": {
              "type": "Identifier",
              "name": "a"
             }
            },
            {
             "type": "StringLiteral",
             "value": "ADD_ERROR",
             "parts": [
              "ADD_ERROR"
             ],
             "isUnicode": [
              false
             ]
            }
           ],
           "names": [],
           "identifiers": []
          }
         },
         {
          "type": "ReturnStatement",
          "expression": {
           "type": "Identifier",
           "name": "c"
          }
         }
        ]
       },
       "visibility": "internal",
       "modifiers": [],
       "override": null,
       "isConstructor": false,
       "isReceiveEther": false,
       "isFallback": false,
       "isVirtual": false,
       "stateMutability": "pure"
      },
      {
       "type": "FunctionDefinition",
       "name": "sqrt",
       "parameters": [
        {
         "type": "VariableDeclaration",
         "typeName": {
          "type": "ElementaryTypeName",
          "name": "uint256",
          "stateMutability": null
         },
         "name": "x",
         "identifier": {
          "type": "Identifier",
          "name": "x"
         },
         "storageLocation": null,
         "isStateVar": false,
         "isIndexed": false,
         "expression": null
        }
       ],
       "returnParameters": [
        {
         "type": "VariableDeclaration",
         "typeName": {
          "type": "ElementaryTypeName",
          "name": "uint256",
          "stateMutability": null
         },
         "name": "y",
         "identifier": {
          "type": "Identifier",
          "name": "y"
         },
         "storageLocation": null,
         "isStateVar": false,
         "isIndexed": false,
         "expression": null
        }
       ],
       "body": {
        "type": "Block",
        "statements": [
         {
          "type": "VariableDeclarationStatement",
          "variables": [
           {
            "type": "VariableDeclaration",
            "typeName": {
             "type": "ElementaryTypeName",
             "name": "uint256",
             "stateMutability": null
            },
            "name": "z",
            "identifier": {
             "type": "Identifier",
             "name": "z"
            },
            "storageLocation": null,
            "isStateVar": false,
            "isIndexed": false,
            "expression": null
           }
          ],
          "initialValue": {
           "type": "BinaryOperation",
           "operator": "+",
           "left": {
            "type": "BinaryOperation",
            "operator": "/",
            "left": {
             "type": "Identifier",
             "name": "x"
            },
            "right": {
             "type": "NumberLiteral",
             "number": "2",
             "subdenomination": null
            }
           },
           "right": {
            "type": "NumberLiteral",
            "number": "1",
            "subdenomination": null
           }
          }
         },
         {
          "type": "ExpressionStatement",
          "expression": {
           "type": "BinaryOperation",
           "operator": "=",
           "left": {
            "type": "Identifier",
            "name": "y"
           },
           "right": {
            "type": "Identifier",
            "name": "x"
           }
          }
         },
         {
          "type": "WhileStatement",
          "condition": {
           "type": "BinaryOperation",
           "operator": "<",
           "left": {
            "type": "Identifier",
            "name": "z"
           },
           "right": {
            "type": "Identifier",
            "name": "y"
           }
          },
          "body": {
           "type": "Block",
           "statements": [
            {
             "type": "ExpressionStatement",
             "expression": {
              "type": "BinaryOperation",
              "operator": "=",
              "left": {
               "type": "Identifier",
               "name": "y"
              },
              "right": {
               "type": "Identifier",
               "name": "z"
              }
             }
            },
            {
             "type": "ExpressionStatement",
             "expression": {
              "type": "BinaryOperation",
              "operator": "=",
              "left": {
               "type": "Identifier",
               "name": "z"
              },
              "right": {
               "type": "BinaryOperation",
               "operator": "/",
               "left": {
                "type": "TupleExpression",
                "components": [
                 {
                  "type": "BinaryOperation",
                  "operator": "+",
                  "left": {
                   "type": "BinaryOperation",
                   "operator": "/",
                   "left": {
                    "type": "Identifier",
                    "name": "x"
                   },
                   "right": {
                    "type": "Identifier",
                    "name": "z"
                   }
                  },
                  "right": {
                   "type": "Identifier",
                   "name": "z"
                  }
                 }
                ],
                "isArray": false
               },
               "right": {
                "type": "NumberLiteral",
                "number": "2",
                "subdenomination": null
               }
              }
             }
            }
           ]
          }
         }
        ]
       },
       "visibility": "internal",
       "modifiers": [],
       "override": null,
       "isConstructor": false,
       "isReceiveEther": false,
       "isFallback": false,
       "isVirtual": false,
       "stateMutability": "pure"
      }
     ],
     "kind": "library"
    },
    {
     "type": "ContractDefinition",
     "name": "InitializableERC20",
     "baseContracts": [],
     "subNodes": [
      {
       "type": "UsingForDeclaration",
       "isGlobal": false,
       "typeName": {
        "type": "ElementaryTypeName",
        "name": "uint256",
        "stateMutability": null
       },
       "libraryName": "SafeMath",
       "functions": [],
       "operators": []
      },
      {
       "type": "StateVariableDeclaration",
       "variables": [
        {
         "type": "VariableDeclaration",
         "typeName": {
          "type": "ElementaryTypeName",
          "name": "string",
          "stateMutability": null
         },
         "name": "name",
         "identifier": {
          "type": "Identifier",
          "name": "name"
         },
         "expression": null,
         "visibility": "public",
         "isStateVar": true,
         "isDeclaredConst": false,
         "isIndexed": false,
         "isImmutable": false,
         "override": null,
         "storageLocation": null
        }
       ],
       "initialValue": null
      },
      {
       "type": "StateVariableDeclaration",
       "variables": [
        {
         "type": "VariableDeclaration",
         "typeName": {
          "type": "ElementaryTypeName",
          "name": "uint256",
          "stateMutability": null
         },
         "name": "decimals",
         "identifier": {
          "type": "Identifier",
          "name": "decimals"
         },
         "expression": null,
         "visibility": "public",
         "isStateVar": true,
         "isDeclaredConst": false,
         "isIndexed": false,
         "isImmutable": false,
         "override": null,
         "storageLocation": null
        }
       ],
       "initialValue": null
      },
      {
       "type": "StateVariableDeclaration",
       "variables": [
        {
         "type": "VariableDeclaration",
         "typeName": {
          "type": "ElementaryTypeName",
          "name": "string",
          "stateMutability": null
         },
         "name": "symbol",
         "identifier": {
          "type": "Identifier",
          "name": "symbol"
         },
         "expression": null,
         "visibility": "public",
         "isStateVar": true,
         "isDeclaredConst": false,
         "isIndexed": false,
         "isImmutable": false,
         "override": null,
         "storageLocation": null
        }
       ],
       "initialValue": null
      },
      {
       "type": "StateVariableDeclaration",
       "variables": [
        {
         "type": "VariableDeclaration",
         "typeName": {
          "type": "ElementaryTypeName",
          "name": "uint256",
          "stateMutability": null
         },
         "name": "totalSupply",
         "identifier": {
          "type": "Identifier",
          "name": "totalSupply"
         },
         "expression": null,
         "visibility": "public",
         "isStateVar": true,
         "isDeclaredConst": false,
         "isIndexed": false,
         "isImmutable": false,
         "override": null,
         "storageLocation": null
        }
       ],
       "initialValue": null
      },
      {
       "type": "StateVariableDeclaration",
       "variables": [
        {
         "type": "VariableDeclaration",
         "typeName": {
          "type": "ElementaryTypeName",
          "name": "bool",
          "stateMutability": null
         },
         "name": "initialized",
         "identifier": {
          "type": "Identifier",
          "name": "initialized"
         },
         "expression": null,
         "visibility": "public",
         "isStateVar": true,
         "isDeclaredConst": false,
         "isIndexed": false,
         "isImmutable": false,
         "override": null,
         "storageLocation": null
        }
       ],
       "initialValue": null
      },
      {
       "type": "StateVariableDeclaration",
       "variables": [
        {
         "type": "VariableDeclaration",
         "typeName": {
          "type": "Mapping",
          "keyType": {
           "type": "ElementaryTypeName",
           "name": "address",
           "stateMutability": null
          },
          "keyName": null,
          "valueType": {
           "type": "ElementaryTypeName",
           "name": "uint256",
           "stateMutability": null
          },
          "valueName": null
         },
         "name": "balances",
         "identifier": {
          "type": "Identifier",
          "name": "balances"
         },
         "expression": null,
         "visibility": "default",
         "isStateVar": true,
         "isDeclaredConst": false,
         "isIndexed": false,
         "isImmutable": false,
         "override": null,
         "storageLocation": null
        }
       ],
       "initialValue": null
      },
      {
       "type": "StateVariableDeclaration",
       "variables": [
        {
         "type": "VariableDeclaration",
         "typeName": {
          "type": "Mapping",
          "keyType": {
           "type": "ElementaryTypeName",
           "name": "address",
           "stateMutability": null
          },
          "keyName": null,
          "valueType": {
           "type": "Mapping",
           "keyType": {
            "type": "ElementaryTypeName",
            "name": "address",
            "stateMutability": null
           },
           "keyName": null,
           "valueType": {
            "type": "ElementaryTypeName",
            "name": "uint256",
            "stateMutability": null
           },
           "valueName": null
          },
          "valueName": null
         },
         "name": "allowed",
         "identifier": {
          "type": "Identifier",
          "name": "allowed"
         },
         "expression": null,
         "visibility": "internal",
         "isStateVar": true,
         "isDeclaredConst": false,
         "isIndexed": false,
         "isImmutable": false,
         "override": null,
         "storageLocation": null
        }
       ],
       "initialValue": null
      },
      {
       "type": "EventDefinition",
       "name": "Transfer",
       "parameters": [
        {
         "type": "VariableDeclaration",
         "typeName": {
          "type": "ElementaryTypeName",
          "name": "address",
          "stateMutability": null
         },
         "name": "from",
         "identifier": {
          "type": "Identifier",
          "name": "from"
         },
         "isStateVar": false,
         "isIndexed": true,
         "storageLocation": null,
         "expression": null
        },
        {
         "type": "VariableDeclaration",
         "typeName": {
          "type": "ElementaryTypeName",
          "name": "address",
          "stateMutability": null
         },
         "name": "to",
         "identifier": {
          "type": "Identifier",
          "name": "to"
         },
         "isStateVar": false,
         "isIndexed": true,
         "storageLocation": null,
         "expression": null
        },
        {
         "type": "VariableDeclaration",
         "typeName": {
          "type": "ElementaryTypeName",
          "name": "uint256",
          "stateMutability": null
         },
         "name": "amount",
         "identifier": {
          "type": "Identifier",
          "name": "amount"
         },
         "isStateVar": false,
         "isIndexed": false,
         "storageLocation": null,
         "expression": null
        }
       ],
       "isAnonymous": false
      },
      {
       "type": "EventDefinition",
       "name": "Approval",
       "parameters": [
        {
         "type": "VariableDeclaration",
         "typeName": {
          "type": "ElementaryTypeName",
          "name": "address",
          "stateMutability": null
         },
         "name": "owner",
         "identifier": {
          "type": "Identifier",
          "name": "owner"
         },
         "isStateVar": false,
         "isIndexed": true,
         "storageLocation": null,
         "expression": null
        },
        {
         "type": "VariableDeclaration",
         "typeName": {
          "type": "ElementaryTypeName",
          "name": "address",
          "stateMutability": null
         },
         "name": "spender",
         "identifier": {
          "type": "Identifier",
          "name": "spender"
         },
         "isStateVar": false,
         "isIndexed": true,
         "storageLocation": null,
         "expression": null
        },
        {
         "type": "VariableDeclaration",
         "typeName": {
          "type": "ElementaryTypeName",
          "name": "uint256",
          "stateMutability": null
         },
         "name": "amount",
         "identifier": {
          "type": "Identifier",
          "name": "amount"
         },
         "isStateVar": false,
         "isIndexed": false,
         "storageLocation": null,
         "expression": null
        }
       ],
       "isAnonymous": false
      },
      {
       "type": "FunctionDefinition",
       "name": "init",
       "parameters": [
        {
         "type": "VariableDeclaration",
         "typeName": {
          "type": "ElementaryTypeName",
          "name": "address",
          "stateMutability": null
         },
         "name": "_creator",
         "identifier": {
          "type": "Identifier",
          "name": "_creator"
         },
         "storageLocation": null,
         "isStateVar": false,
         "isIndexed": false,
         "expression": null
        },
        {
         "type": "VariableDeclaration",
         "typeName": {
          "type": "ElementaryTypeName",
          "name": "uint256",
          "stateMutability": null
         },
         "name": "_totalSupply",
         "identifier": {
          "type": "Identifier",
          "name": "_totalSupply"
         },
         "storageLocation": null,
         "isStateVar": false,
         "isIndexed": false,
         "expression": null
        },
        {
         "type": "VariableDeclaration",
         "typeName": {
          "type": "ElementaryTypeName",
          "name": "string",
          "stateMutability": null
         },
         "name": "_name",
         "identifier": {
          "type": "Identifier",
          "name": "_name"
         },
         "storageLocation": "memory",
         "isStateVar": false,
         "isIndexed": false,
         "expression": null
        },
        {
         "type": "VariableDeclaration",
         "typeName": {
          "type": "ElementaryTypeName",
          "name": "string",
          "stateMutability": null
         },
         "name": "_symbol",
         "identifier": {
          "type": "Identifier",
          "name": "_symbol"
         },
         "storageLocation": "memory",
         "isStateVar": false,
         "isIndexed": false,
         "expression": null
        },
        {
         "type": "VariableDeclaration",
         "typeName": {
          "type": "ElementaryTypeName",
          "name": "uint256",
          "stateMutability": null
         },
         "name": "_decimals",
         "identifier": {
          "type": "Identifier",
          "name": "_decimals"
         },
         "storageLocation": null,
         "isStateVar": false,
         "isIndexed": false,
         "expression": null
        }
       ],
       "returnParameters": null,
       "body": {
        "type": "Block",
        "statements": [
         {
          "type": "ExpressionStatement",
          "expression": {
           "type": "FunctionCall",
           "expression": {
            "type": "Identifier",
            "name": "require"
           },
           "arguments": [
            {
             "type": "UnaryOperation",
             "operator": "!",
             "subExpression": {
              "type": "Identifier",
              "name": "initialized"
             },
             "isPrefix": true
            },
            {
             "type": "StringLiteral",
             "value": "TOKEN_INITIALIZED",
             "parts": [
              "TOKEN_INITIALIZED"
             ],
             "isUnicode": [
              false
             ]
            }
           ],
           "names": [],
           "identifiers": []
          }
         },
         {
          "type": "ExpressionStatement",
          "expression": {
           "type": "BinaryOperation",
           "operator": "=",
           "left": {
            "type": "Identifier",
            "name": "initialized"
           },
           "right": {
            "type": "BooleanLiteral",
            "value": true
           }
          }
         },
         {
          "type": "ExpressionStatement",
          "expression": {
           "type": "BinaryOperation",
           "operator": "=",
           "left": {
            "type": "Identifier",
            "name": "totalSupply"
           },
           "right": {
            "type": "Identifier",
            "name": "_totalSupply"
           }
          }
         },
         {
          "type": "ExpressionStatement",
          "expression": {
           "type": "BinaryOperation",
           "operator": "=",
           "left": {
            "type": "IndexAccess",
            "base": {
             "type": "Identifier",
             "name": "balances"
            },
            "index": {
             "type": "Identifier",
             "name": "_creator"
            }
           },
           "right": {
            "type": "Identifier",
            "name": "_totalSupply"
           }
          }
         },
         {
          "type": "ExpressionStatement",
          "expression": {
           "type": "BinaryOperation",
           "operator": "=",
           "left": {
            "type": "Identifier",
            "name": "name"
           },
           "right": {
            "type": "Identifier",
            "name": "_name"
           }
          }
         },
         {
          "type": "ExpressionStatement",
          "expression": {
           "type": "BinaryOperation",
           "operator": "=",
           "left": {
            "type": "Identifier",
            "name": "symbol"
           },
           "right": {
            "type": "Identifier",
            "name": "_symbol"
           }
          }
         },
         {
          "type": "ExpressionStatement",
          "expression": {
           "type": "BinaryOperation",
           "operator": "=",
           "left": {
            "type": "Identifier",
            "name": "decimals"
           },
           "right": {
            "type": "Identifier",
            "name": "_decimals"
           }
          }
         },
         {
          "type": "EmitStatement",
          "eventCall": {
           "type": "FunctionCall",
           "expression": {
            "type": "Identifier",
            "name": "Transfer"
           },
           "arguments": [
            {
             "type": "FunctionCall",
             "expression": {
              "type": "Identifier",
              "name": "address"
             },
             "arguments": [
              {
               "type": "NumberLiteral",
               "number": "0",
               "subdenomination": null
              }
             ],
             "names": [],
             "identifiers": []
            },
            {
             "type": "Identifier",
             "name": "_creator"
            },
            {
             "type": "Identifier",
             "name": "_totalSupply"
            }
           ],
           "names": [],
           "identifiers": []
          }
         }
        ]
       },
       "visibility": "public",
       "modifiers": [],
       "override": null,
       "isConstructor": false,
       "isReceiveEther": false,
       "isFallback": false,
       "isVirtual": false,
       "stateMutability": null
      },
      {
       "type": "FunctionDefinition",
       "name": "transfer",
       "parameters": [
        {
         "type": "VariableDeclaration",
         "typeName": {
          "type": "ElementaryTypeName",
          "name": "address",
          "stateMutability": null
         },
         "name": "to",
         "identifier": {
          "type": "Identifier",
          "name": "to"
         },
         "storageLocation": null,
         "isStateVar": false,
         "isIndexed": false,
         "expression": null
        },
        {
         "type": "VariableDeclaration",
         "typeName": {
          "type": "ElementaryTypeName",
          "name": "uint256",
          "stateMutability": null
         },
         "name": "amount",
         "identifier": {
          "type": "Identifier",
          "name": "amount"
         },
         "storageLocation": null,
         "isStateVar": false,
         "isIndexed": false,
         "expression": null
        }
       ],
       "returnParameters": [
        {
         "type": "VariableDeclaration",
         "typeName": {
          "type": "ElementaryTypeName",
          "name": "bool",
          "stateMutability": null
         },
         "name": null,
         "identifier": null,
         "storageLocation": null,
         "isStateVar": false,
         "isIndexed": false,
         "expression": null
        }
       ],
       "body": {
        "type": "Block",
        "statements": [
         {
          "type": "ExpressionStatement",
          "expression": {
           "type": "FunctionCall",
           "expression": {
            "type": "Identifier",
            "name": "require"
           },
           "arguments": [
            {
             "type": "BinaryOperation",
             "operator": "!=",
             "left": {
              "type": "Identifier",
              "name": "to"
             },
             "right": {
              "type": "FunctionCall",
              "expression": {
               "type": "Identifier",
               "name": "address"
              },
              "arguments": [
               {
                "type": "NumberLiteral",
                "number": "0",
                "subdenomination": null
               }
              ],
              "names": [],
              "identifiers": []
             }
            },
            {
             "type": "StringLiteral",
             "value": "TO_ADDRESS_IS_EMPTY",
             "parts": [
              "TO_ADDRESS_IS_EMPTY"
             ],
             "isUnicode": [
              false
             ]
            }
           ],
           "names": [],
           "identifiers": []
          }
         },
         {
          "type": "ExpressionStatement",
          "expression": {
           "type": "FunctionCall",
           "expression": {
            "type": "Identifier",
            "name": "require"
           },
           "arguments": [
            {
             "type": "BinaryOperation",
             "operator": "<=",
             "left": {
              "type": "Identifier",
              "name": "amount"
             },
             "right": {
              "type": "IndexAccess",
              "base": {
               "type": "Identifier",
               "name": "balances"
              },
              "index": {
               "type": "MemberAccess",
               "expression": {
                "type": "Identifier",
                "name": "msg"
               },
               "memberName": "sender"
              }
             }
            },
            {
             "type": "StringLiteral",
             "value": "BALANCE_NOT_ENOUGH",
             "parts": [
              "BALANCE_NOT_ENOUGH"
             ],
             "isUnicode": [
              false
             ]
            }
           ],
           "names": [],
           "identifiers": []
          }
         },
         {
          "type": "ExpressionStatement",
          "expression": {
           "type": "BinaryOperation",
           "operator": "=",
           "left": {
            "type": "IndexAccess",
            "base": {
             "type": "Identifier",
             "name": "balances"
            },
            "index": {
             "type": "MemberAccess",
             "expression": {
              "type": "Identifier",
              "name": "msg"
             },
             "memberName": "sender"
            }
           },
           "right": {
            "type": "FunctionCall",
            "expression": {
             "type": "MemberAccess",
             "expression": {
              "type": "IndexAccess",
              "base": {
               "type": "Identifier",
               "name": "balances"
              },
              "index": {
               "type": "MemberAccess",
               "expression": {
                "type": "Identifier",
                "name": "msg"
               },
               "memberName": "sender"
              }
             },
             "memberName": "sub"
            },
            "arguments": [
             {
              "type": "Identifier",
              "name": "amount"
             }
            ],
            "names": [],
            "identifiers": []
           }
          }
         },
         {
          "type": "ExpressionStatement",
          "expression": {
           "type": "BinaryOperation",
           "operator": "=",
           "left": {
            "type": "IndexAccess",
            "base": {
             "type": "Identifier",
             "name": "balances"
            },
            "index": {
             "type": "Identifier",
             "name": "to"
            }
           },
           "right": {
            "type": "FunctionCall",
            "expression": {
             "type": "MemberAccess",
             "expression": {
              "type": "IndexAccess",
              "base": {
               "type": "Identifier",
               "name": "balances"
              },
              "index": {
               "type": "Identifier",
               "name": "to"
              }
             },
             "memberName": "add"
            },
            "arguments": [
             {
              "type": "Identifier",
              "name": "amount"
             }
            ],
            "names": [],
            "identifiers": []
           }
          }
         },
         {
          "type": "EmitStatement",
          "eventCall": {
           "type": "FunctionCall",
           "expression": {
            "type": "Identifier",
            "name": "Transfer"
           },
           "arguments": [
            {
             "type": "MemberAccess",
             "expression": {
              "type": "Identifier",
              "name": "msg"
             },
             "memberName": "sender"
            },
            {
             "type": "Identifier",
             "name": "to"
            },
            {
             "type": "Identifier",
             "name": "amount"
            }
           ],
           "names": [],
           "identifiers": []
          }
         },
         {
          "type": "ReturnStatement",
          "expression": {
           "type": "BooleanLiteral",
           "value": true
          }
         }
        ]
       },
       "visibility": "public",
       "modifiers": [],
       "override": null,
       "isConstructor": false,
       "isReceiveEther": false,
       "isFallback": false,
       "isVirtual": false,
       "stateMutability": null
      },
      {
       "type": "FunctionDefinition",
       "name": "balanceOf",
       "parameters": [
        {
         "type": "VariableDeclaration",
         "typeName": {
          "type": "ElementaryTypeName",
          "name": "address",
          "stateMutability": null
         },
         "name": "owner",
         "identifier": {
          "type": "Identifier",
          "name": "owner"
         },
         "storageLocation": null,
         "isStateVar": false,
         "isIndexed": false,
         "expression": null
        }
       ],
       "returnParameters": [
        {
         "type": "VariableDeclaration",
         "typeName": {
          "type": "ElementaryTypeName",
          "name": "uint256",
          "stateMutability": null
         },
         "name": "balance",
         "identifier": {
          "type": "Identifier",
          "name": "balance"
         },
         "storageLocation": null,
         "isStateVar": false,
         "isIndexed": false,
         "expression": null
        }
       ],
       "body": {
        "type": "Block",
        "statements": [
         {
          "type": "ReturnStatement",
          "expression": {
           "type": "IndexAccess",
           "base": {
            "type": "Identifier",
            "name": "balances"
           },
           "index": {
            "type": "Identifier",
            "name": "owner"
           }
          }
         }
        ]
       },
       "visibility": "public",
       "modifiers": [],
       "override": null,
       "isConstructor": false,
       "isReceiveEther": false,
       "isFallback": false,
       "isVirtual": false,
       "stateMutability": "view"
      },
      {
       "type": "FunctionDefinition",
       "name": "transferFrom",
       "parameters": [
        {
         "type": "VariableDeclaration",
         "typeName": {
          "type": "ElementaryTypeName",
          "name": "address",
          "stateMutability": null
         },
         "name": "from",
         "identifier": {
          "type": "Identifier",
          "name": "from"
         },
         "storageLocation": null,
         "isStateVar": false,
         "isIndexed": false,
         "expression": null
        },
        {
         "type": "VariableDeclaration",
         "typeName": {
          "type": "ElementaryTypeName",
          "name": "address",
          "stateMutability": null
         },
         "name": "to",
         "identifier": {
          "type": "Identifier",
          "name": "to"
         },
         "storageLocation": null,
         "isStateVar": false,
         "isIndexed": false,
         "expression": null
        },
        {
         "type": "VariableDeclaration",
         "typeName": {
          "type": "ElementaryTypeName",
          "name": "uint256",
          "stateMutability": null
         },
         "name": "amount",
         "identifier": {
          "type": "Identifier",
          "name": "amount"
         },
         "storageLocation": null,
         "isStateVar": false,
         "isIndexed": false,
         "expression": null
        }
       ],
       "returnParameters": [
        {
         "type": "VariableDeclaration",
         "typeName": {
          "type": "ElementaryTypeName",
          "name": "bool",
          "stateMutability": null
         },
         "name": null,
         "identifier": null,
         "storageLocation": null,
         "isStateVar": false,
         "isIndexed": false,
         "expression": null
        }
       ],
       "body": {
        "type": "Block",
        "statements": [
         {
          "type": "ExpressionStatement",
          "expression": {
           "type": "FunctionCall",
           "expression": {
            "type": "Identifier",
            "name": "require"
           },
           "arguments": [
            {
             "type": "BinaryOperation",
             "operator": "!=",
             "left": {
              "type": "Identifier",
              "name": "to"
             },
             "right": {
              "type": "FunctionCall",
              "expression": {
               "type": "Identifier",
               "name": "address"
              },
              "arguments": [
               {
                "type": "NumberLiteral",
                "number": "0",
                "subdenomination": null
               }
              ],
              "names": [],
              "identifiers": []
             }
            },
            {
             "type": "StringLiteral",
             "value": "TO_ADDRESS_IS_EMPTY",
             "parts": [
              "TO_ADDRESS_IS_EMPTY"
             ],
             "isUnicode": [
              false
             ]
            }
           ],
           "names": [],
           "identifiers": []
          }
         },
         {
          "type": "ExpressionStatement",
          "expression": {
           "type": "FunctionCall",
           "expression": {
            "type": "Identifier",
            "name": "require"
           },
           "arguments": [
            {
             "type": "BinaryOperation",
             "operator": "<=",
             "left": {
              "type": "Identifier",
              "name": "amount"
             },
             "right": {
              "type": "IndexAccess",
              "base": {
               "type": "Identifier",
               "name": "balances"
              },
              "index": {
               "type": "Identifier",
               "name": "from"
              }
             }
            },
            {
             "type": "StringLiteral",
             "value": "BALANCE_NOT_ENOUGH",
             "parts": [
              "BALANCE_NOT_ENOUGH"
             ],
             "isUnicode": [
              false
             ]
            }
           ],
           "names": [],
           "identifiers": []
          }
         },
         {
          "type": "ExpressionStatement",
          "expression": {
           "type": "FunctionCall",
           "expression": {
            "type": "Identifier",
            "name": "require"
           },
           "arguments": [
            {
             "type": "BinaryOperation",
             "operator": "<=",
             "left": {
              "type": "Identifier",
              "name": "amount"
             },
             "right": {
              "type": "IndexAccess",
              "base": {
               "type": "IndexAccess",
               "base": {
                "type": "Identifier",
                "name": "allowed"
               },
               "index": {
                "type": "Identifier",
                "name": "from"
               }
              },
              "index": {
               "type": "MemberAccess",
               "expression": {
                "type": "Identifier",
                "name": "msg"
               },
               "memberName": "sender"
              }
             }
            },
            {
             "type": "StringLiteral",
             "value": "ALLOWANCE_NOT_ENOUGH",
             "parts": [
              "ALLOWANCE_NOT_ENOUGH"
             ],
             "isUnicode": [
              false
             ]
            }
           ],
           "names": [],
           "identifiers": []
          }
         },
         {
          "type": "ExpressionStatement",
          "expression": {
           "type": "BinaryOperation",
           "operator": "=",
           "left": {
            "type": "IndexAccess",
            "base": {
             "type": "Identifier",
             "name": "balances"
            },
            "index": {
             "type": "Identifier",
             "name": "from"
            }
           },
           "right": {
            "type": "FunctionCall",
            "expression": {
             "type": "MemberAccess",
             "expression": {
              "type": "IndexAccess",
              "base": {
               "type": "Identifier",
               "name": "balances"
              },
              "index": {
               "type": "Identifier",
               "name": "from"
              }
             },
             "memberName": "sub"
            },
            "arguments": [
             {
              "type": "Identifier",
              "name": "amount"
             }
            ],
            "names": [],
            "identifiers": []
           }
          }
         },
         {
          "type": "ExpressionStatement",
          "expression": {
           "type": "BinaryOperation",
           "operator": "=",
           "left": {
            "type": "IndexAccess",
            "base": {
             "type": "Identifier",
             "name": "balances"
            },
            "index": {
             "type": "Identifier",
             "name": "to"
            }
           },
           "right": {
            "type": "FunctionCall",
            "expression": {
             "type": "MemberAccess",
             "expression": {
              "type": "IndexAccess",
              "base": {
               "type": "Identifier",
               "name": "balances"
              },
              "index": {
               "type": "Identifier",
               "name": "to"
              }
             },
             "memberName": "add"
            },
            "arguments": [
             {
              "type": "Identifier",
              "name": "amount"
             }
            ],
            "names": [],
            "identifiers": []
           }
          }
         },
         {
          "type": "ExpressionStatement",
          "expression": {
           "type": "BinaryOperation",
           "operator": "=",
           "left": {
            "type": "IndexAccess",
            "base": {
             "type": "IndexAccess",
             "base": {
              "type": "Identifier",
              "name": "allowed"
             },
             "index": {
              "type": "Identifier",
              "name": "from"
             }
            },
            "index": {
             "type": "MemberAccess",
             "expression": {
              "type": "Identifier",
              "name": "msg"
             },
             "memberName": "sender"
            }
           },
           "right": {
            "type": "FunctionCall",
            "expression": {
             "type": "MemberAccess",
             "expression": {
              "type": "IndexAccess",
              "base": {
               "type": "IndexAccess",
               "base": {
                "type": "Identifier",
                "name": "allowed"
               },
               "index": {
                "type": "Identifier",
                "name": "from"
               }
              },
              "index": {
               "type": "MemberAccess",
               "expression": {
                "type": "Identifier",
                "name": "msg"
               },
               "memberName": "sender"
              }
             },
             "memberName": "sub"
            },
            "arguments": [
             {
              "type": "Identifier",
              "name": "amount"
             }
            ],
            "names": [],
            "identifiers": []
           }
          }
         },
         {
          "type": "EmitStatement",
          "eventCall": {
           "type": "FunctionCall",
           "expression": {
            "type": "Identifier",
            "name": "Transfer"
           },
           "arguments": [
            {
             "type": "Identifier",
             "name": "from"
            },
            {
             "type": "Identifier",
             "name": "to"
            },
            {
             "type": "Identifier",
             "name": "amount"
            }
           ],
           "names": [],
           "identifiers": []
          }
         },
         {
          "type": "ReturnStatement",
          "expression": {
           "type": "BooleanLiteral",
           "value": true
          }
         }
        ]
       },
       "visibility": "public",
       "modifiers": [],
       "override": null,
       "isConstructor": false,
       "isReceiveEther": false,
       "isFallback": false,
       "isVirtual": false,
       "stateMutability": null
      },
      {
       "type": "FunctionDefinition",
       "name": "approve",
       "parameters": [
        {
         "type": "VariableDeclaration",
         "typeName": {
          "type": "ElementaryTypeName",
          "name": "address",
          "stateMutability": null
         },
         "name": "spender",
         "identifier": {
          "type": "Identifier",
          "name": "spender"
         },
         "storageLocation": null,
         "isStateVar": false,
         "isIndexed": false,
         "expression": null
        },
        {
         "type": "VariableDeclaration",
         "typeName": {
          "type": "ElementaryTypeName",
          "name": "uint256",
          "stateMutability": null
         },
         "name": "amount",
         "identifier": {
          "type": "Identifier",
          "name": "amount"
         },
         "storageLocation": null,
         "isStateVar": false,
         "isIndexed": false,
         "expression": null
        }
       ],
       "returnParameters": [
        {
         "type": "VariableDeclaration",
         "typeName": {
          "type": "ElementaryTypeName",
          "name": "bool",
          "stateMutability": null
         },
         "name": null,
         "identifier": null,
         "storageLocation": null,
         "isStateVar": false,
         "isIndexed": false,
         "expression": null
        }
       ],
       "body": {
        "type": "Block",
        "statements": [
         {
          "type": "ExpressionStatement",
          "expression": {
           "type": "BinaryOperation",
           "operator": "=",
           "left": {
            "type": "IndexAccess",
            "base": {
             "type": "IndexAccess",
             "base": {
              "type": "Identifier",
              "name": "allowed"
             },
             "index": {
              "type": "MemberAccess",
              "expression": {
               "type": "Identifier",
               "name": "msg"
              },
              "memberName": "sender"
             }
            },
            "index": {
             "type": "Identifier",
             "name": "spender"
            }
           },
           "right": {
            "type": "Identifier",
            "name": "amount"
           }
          }
         },
         {
          "type": "EmitStatement",
          "eventCall": {
           "type": "FunctionCall",
           "expression": {
            "type": "Identifier",
            "name": "Approval"
           },
           "arguments": [
            {
             "type": "MemberAccess",
             "expression": {
              "type": "Identifier",
              "name": "msg"
             },
             "memberName": "sender"
            },
            {
             "type": "Identifier",
             "name": "spender"
            },
            {
             "type": "Identifier",
             "name": "amount"
            }
           ],
           "names": [],
           "identifiers": []
          }
         },
         {
          "type": "ReturnStatement",
          "expression": {
           "type": "BooleanLiteral",
           "value": true
          }
         }
        ]
       },
       "visibility": "public",
       "modifiers": [],
       "override": null,
       "isConstructor": false,
       "isReceiveEther": false,
       "isFallback": false,
       "isVirtual": false,
       "stateMutability": null
      },
      {
       "type": "FunctionDefinition",
       "name": "allowance",
       "parameters": [
        {
         "type": "VariableDeclaration",
         "typeName": {
          "type": "ElementaryTypeName",
          "name": "address",
          "stateMutability": null
         },
         "name": "owner",
         "identifier": {
          "type": "Identifier",
          "name": "owner"
         },
         "storageLocation": null,
         "isStateVar": false,
         "isIndexed": false,
         "expression": null
        },
        {
         "type": "VariableDeclaration",
         "typeName": {
          "type": "ElementaryTypeName",
          "name": "address",
          "stateMutability": null
         },
         "name": "spender",
         "identifier": {
          "type": "Identifier",
          "name": "spender"
         },
         "storageLocation": null,
         "isStateVar": false,
         "isIndexed": false,
         "expression": null
        }
       ],
       "returnParameters": [
        {
         "type": "VariableDeclaration",
         "typeName": {
          "type": "ElementaryTypeName",
          "name": "uint256",
          "stateMutability": null
         },
         "name": null,
         "identifier": null,
         "storageLocation": null,
         "isStateVar": false,
         "isIndexed": false,
         "expression": null
        }
       ],
       "body": {
        "type": "Block",
        "statements": [
         {
          "type": "ReturnStatement",
          "expression": {
           "type": "IndexAccess",
           "base": {
            "type": "IndexAccess",
            "base": {
             "type": "Identifier",
             "name": "allowed"
            },
            "index": {
             "type": "Identifier",
             "name": "owner"
            }
           },
           "index": {
            "type": "Identifier",
            "name": "spender"
           }
          }
         }
        ]
       },
       "visibility": "public",
       "modifiers": [],
       "override": null,
       "isConstructor": false,
       "isReceiveEther": false,
       "isFallback": false,
       "isVirtual": false,
       "stateMutability": "view"
      }
     ],
     "kind": "contract"
    }
   ]
  }
 }
]